ai/__init__.py
ai/ai_client.py
ai/ai_client_config.py
ai/ai_client_factory.py
ai/aws/__init__.py
ai/aws/bedrock_client.py
ai/aws/bedrock_client_config.py
ai/aws/anthropic/__init__.py
ai/aws/anthropic/claude_client.py
ai/aws/anthropic/claude_client_config.py
ai/openai/__init__.py
ai/openai/openai_client.py
ai/openai/openai_config.py
cli/__init__.py
cli/app.py
cli/code_app.py
cli/file_app.py
cli/process_app.py
cli/prompt_app.py
cmd/__init__.py
cmd/command_runner.py
db/__init__.py
db/file_history_db.py
db/history_db.py
db/process_file_db.py
db/prompt_db.py
db/shared_file_db.py
instruction/__init__.py
instruction/instruction_model.py
instruction/instructions/__init__.py
instruction/instructions/instruction_review.py
instruction/instructions/mypy.py
instruction/instructions/readme.py
instruction/instructions/response_format.py
instruction/instructions/typer_log.py
instruction/instructions/unit_test.py
sasori-0.1.1.dist-info/licenses/LICENSE
util/__init__.py
util/file_util.py
util/session_util.py
util/string_util.py
sasori-0.1.1.dist-info/METADATA
sasori-0.1.1.dist-info/WHEEL
sasori-0.1.1.dist-info/entry_points.txt
sasori-0.1.1.dist-info/top_level.txt
sasori-0.1.1.dist-info/RECORD
