Metadata-Version: 2.4
Name: sasori
Version: 0.1.1
Summary: CLI toolkit for managing prompts, files, and AI-powered workflows
Author-email: Gustavo Gardusi <gustavo.gardusi@gmail.com>
License: MIT License
Project-URL: Homepage, https://github.com/gardusig/sasoriCLI
Classifier: Programming Language :: Python :: 3
Classifier: Programming Language :: Python :: 3.9
Classifier: License :: OSI Approved :: MIT License
Classifier: Operating System :: OS Independent
Requires-Python: >=3.8
License-File: LICENSE
Requires-Dist: openai
Requires-Dist: python-dotenv
Requires-Dist: rich
Requires-Dist: typer[all]
Requires-Dist: boto3
Requires-Dist: pyperclip
Provides-Extra: dev
Requires-Dist: pytest; extra == "dev"
Requires-Dist: mypy; extra == "dev"
Requires-Dist: black; extra == "dev"
Requires-Dist: flake8; extra == "dev"
Dynamic: license-file
